Metadata-Version: 1.0
Name: triethai
Version: 1.1
Summary: Trie for search, approximate search, and spell correction written in Python
Home-page: https://github.com/peune/triethai.git
Author: Sanparith Marukatat
Author-email: sanparith.marukatat@nectec.or.th
License: MIT
Platform: UNKNOWN
